citronella/__init__.py
citronella/deprecated.py
citronella/logger.py
citronella/page_decorator.py
citronella/page_validator.py
citronella/ui.py
citronella/web_page.py
citronella/web_ui.py
citronella-1.0.1.dist-info/METADATA
citronella-1.0.1.dist-info/WHEEL
citronella-1.0.1.dist-info/top_level.txt
citronella-1.0.1.dist-info/RECORD
