Metadata-Version: 2.1
Name: citronella
Version: 1.0.1
Summary: Webdriver Extension with Page Object Wrapper
Home-page: https://github.com/heyclore/citronella/tree/main/python#readme
Author: heyclore
Author-email: cloore@gmail.com
License: MIT
Project-URL: Source, https://github.com/heyclore/citronella/tree/main/python
Keywords: test,unittest,pytest,webdriver,appium,selenium
Classifier: Development Status :: 5 - Production/Stable
Classifier: Intended Audience :: Developers
Classifier: Topic :: Software Development :: Testing
Classifier: License :: OSI Approved :: MIT License
Classifier: Programming Language :: Python
Classifier: Programming Language :: Python :: 3.7
Classifier: Programming Language :: Python :: 3.8
Classifier: Programming Language :: Python :: 3.9
Requires-Python: ~=3.7
Requires-Dist: selenium
